<?xml version="1.0" encoding="UTF-8"?>
<!DOCTYPE plist PUBLIC "-//Apple//DTD PLIST 1.0//EN" "http://www.apple.com/DTDs/PropertyList-1.0.dtd"/>

<plist version="1.0">
    <dict>
        <key>ROOT</key>
        <array>
            <dict>
                <key>id</key>
                <string>217</string>
                <key>Emitters</key>
                <dict>
                    <key>emitters</key>
                    <array>
                        <string>221</string>
                    </array>
                </dict>
            </dict>
            <dict>
                <key>id</key>
                <string>231</string>
                <key>Emitters</key>
                <dict>
                    <key>emitters</key>
                    <array>
                        <string>233</string>
                    </array>
                </dict>
            </dict>
            <dict>
                <key>id</key>
                <string>584</string>
                <key>Emitters</key>
                <dict>
                    <key>emitters</key>
                    <array>
                        <string>586</string>
                    </array>
                </dict>
            </dict>
            <dict>
                <key>id</key>
                <string>945</string>
                <key>Emitters</key>
                <dict>
                    <key>emitters</key>
                    <array>
                        <string>947</string>
                    </array>
                </dict>
            </dict>
            <dict>
                <key>id</key>
                <string>951</string>
                <key>Emitters</key>
                <dict>
                    <key>emitters</key>
                    <array>
                        <string>953</string>
                        <string>956</string>
                    </array>
                </dict>
            </dict>
            <dict>
                <key>id</key>
                <string>984</string>
                <key>Emitters</key>
                <dict>
                    <key>emitters</key>
                    <array>
                        <string>990</string>
                    </array>
                </dict>
            </dict>
            <dict>
                <key>id</key>
                <string>1047</string>
                <key>Emitters</key>
                <dict>
                    <key>emitters</key>
                    <array>
                        <string>1049</string>
                    </array>
                </dict>
            </dict>
            <dict>
                <key>id</key>
                <string>1251</string>
                <key>Emitters</key>
                <dict>
                    <key>emitters</key>
                    <array>
                        <string>1253</string>
                    </array>
                </dict>
            </dict>
            <dict>
                <key>id</key>
                <string>1317</string>
                <key>Emitters</key>
                <dict>
                    <key>emitters</key>
                    <array>
                        <string>1319</string>
                        <string>1320</string>
                    </array>
                </dict>
            </dict>
            <dict>
                <key>id</key>
                <string>2393</string>
                <key>Emitters</key>
                <dict>
                    <key>emitters</key>
                    <array>
                        <string>2395</string>
                    </array>
                </dict>
            </dict>
            <dict>
                <key>id</key>
                <string>2558</string>
                <key>Emitters</key>
                <dict>
                    <key>emitters</key>
                    <array>
                        <string>2560</string>
                    </array>
                </dict>
            </dict>
            <dict>
                <key>id</key>
                <string>2564</string>
                <key>Emitters</key>
                <dict>
                    <key>emitters</key>
                    <array>
                        <string>2566</string>
                    </array>
                </dict>
            </dict>
            <dict>
                <key>id</key>
                <string>2570</string>
                <key>Emitters</key>
                <dict>
                    <key>emitters</key>
                    <array>
                        <string>2572</string>
                    </array>
                </dict>
            </dict>
            <dict>
                <key>id</key>
                <string>2576</string>
                <key>Emitters</key>
                <dict>
                    <key>emitters</key>
                    <array>
                        <string>2578</string>
                    </array>
                </dict>
            </dict>
            <dict>
                <key>id</key>
                <string>2582</string>
                <key>Emitters</key>
                <dict>
                    <key>emitters</key>
                    <array>
                        <string>2584</string>
                    </array>
                </dict>
            </dict>
            <dict>
                <key>id</key>
                <string>2588</string>
                <key>Emitters</key>
                <dict>
                    <key>emitters</key>
                    <array>
                        <string>2590</string>
                    </array>
                </dict>
            </dict>
            <dict>
                <key>id</key>
                <string>2594</string>
                <key>Emitters</key>
                <dict>
                    <key>emitters</key>
                    <array>
                        <string>2596</string>
                    </array>
                </dict>
            </dict>
            <dict>
                <key>id</key>
                <string>2600</string>
                <key>Emitters</key>
                <dict>
                    <key>emitters</key>
                    <array>
                        <string>2602</string>
                    </array>
                </dict>
            </dict>
            <dict>
                <key>id</key>
                <string>2606</string>
                <key>Emitters</key>
                <dict>
                    <key>emitters</key>
                    <array>
                        <string>2608</string>
                    </array>
                </dict>
            </dict>
            <dict>
                <key>id</key>
                <string>2612</string>
                <key>Emitters</key>
                <dict>
                    <key>emitters</key>
                    <array>
                        <string>2614</string>
                    </array>
                </dict>
            </dict>
            <dict>
                <key>id</key>
                <string>2618</string>
                <key>Emitters</key>
                <dict>
                    <key>emitters</key>
                    <array>
                        <string>2620</string>
                    </array>
                </dict>
            </dict>
            <dict>
                <key>id</key>
                <string>2624</string>
                <key>Emitters</key>
                <dict>
                    <key>emitters</key>
                    <array>
                        <string>2626</string>
                    </array>
                </dict>
            </dict>
            <dict>
                <key>id</key>
                <string>2630</string>
                <key>Emitters</key>
                <dict>
                    <key>emitters</key>
                    <array>
                        <string>2632</string>
                    </array>
                </dict>
            </dict>
            <dict>
                <key>id</key>
                <string>2636</string>
                <key>Emitters</key>
                <dict>
                    <key>emitters</key>
                    <array>
                        <string>2638</string>
                    </array>
                </dict>
            </dict>
            <dict>
                <key>id</key>
                <string>2642</string>
                <key>Emitters</key>
                <dict>
                    <key>emitters</key>
                    <array>
                        <string>2644</string>
                    </array>
                </dict>
            </dict>
            <dict>
                <key>id</key>
                <string>2648</string>
                <key>Emitters</key>
                <dict>
                    <key>emitters</key>
                    <array>
                        <string>2650</string>
                    </array>
                </dict>
            </dict>
            <dict>
                <key>id</key>
                <string>2654</string>
                <key>Emitters</key>
                <dict>
                    <key>emitters</key>
                    <array>
                        <string>2656</string>
                    </array>
                </dict>
            </dict>
            <dict>
                <key>id</key>
                <string>3205</string>
                <key>Emitters</key>
                <dict>
                    <key>emitters</key>
                    <array>
                        <string>3207</string>
                    </array>
                </dict>
            </dict>
            <dict>
                <key>id</key>
                <string>3382</string>
                <key>Emitters</key>
                <dict>
                    <key>emitters</key>
                    <array>
                        <string>3384</string>
                    </array>
                </dict>
            </dict>
            <dict>
                <key>id</key>
                <string>3388</string>
                <key>Emitters</key>
                <dict>
                    <key>emitters</key>
                    <array>
                        <string>3390</string>
                    </array>
                </dict>
            </dict>
            <dict>
                <key>id</key>
                <string>3394</string>
                <key>Emitters</key>
                <dict>
                    <key>emitters</key>
                    <array>
                        <string>3396</string>
                    </array>
                </dict>
            </dict>
            <dict>
                <key>id</key>
                <string>3400</string>
                <key>Emitters</key>
                <dict>
                    <key>emitters</key>
                    <array>
                        <string>3402</string>
                    </array>
                </dict>
            </dict>
            <dict>
                <key>id</key>
                <string>3406</string>
                <key>Emitters</key>
                <dict>
                    <key>emitters</key>
                    <array>
                        <string>3408</string>
                    </array>
                </dict>
            </dict>
            <dict>
                <key>id</key>
                <string>3412</string>
                <key>Emitters</key>
                <dict>
                    <key>emitters</key>
                    <array>
                        <string>3414</string>
                    </array>
                </dict>
            </dict>
            <dict>
                <key>id</key>
                <string>3418</string>
                <key>Emitters</key>
                <dict>
                    <key>emitters</key>
                    <array>
                        <string>3420</string>
                    </array>
                </dict>
            </dict>
            <dict>
                <key>id</key>
                <string>3424</string>
                <key>Emitters</key>
                <dict>
                    <key>emitters</key>
                    <array>
                        <string>3426</string>
                    </array>
                </dict>
            </dict>
            <dict>
                <key>id</key>
                <string>3430</string>
                <key>Emitters</key>
                <dict>
                    <key>emitters</key>
                    <array>
                        <string>3432</string>
                    </array>
                </dict>
            </dict>
            <dict>
                <key>id</key>
                <string>3436</string>
                <key>Emitters</key>
                <dict>
                    <key>emitters</key>
                    <array>
                        <string>3438</string>
                    </array>
                </dict>
            </dict>
            <dict>
                <key>id</key>
                <string>3442</string>
                <key>Emitters</key>
                <dict>
                    <key>emitters</key>
                    <array>
                        <string>3444</string>
                    </array>
                </dict>
            </dict>
            <dict>
                <key>id</key>
                <string>3448</string>
                <key>Emitters</key>
                <dict>
                    <key>emitters</key>
                    <array>
                        <string>3450</string>
                    </array>
                </dict>
            </dict>
            <dict>
                <key>id</key>
                <string>3454</string>
                <key>Emitters</key>
                <dict>
                    <key>emitters</key>
                    <array>
                        <string>3456</string>
                    </array>
                </dict>
            </dict>
            <dict>
                <key>id</key>
                <string>3460</string>
                <key>Emitters</key>
                <dict>
                    <key>emitters</key>
                    <array>
                        <string>3462</string>
                    </array>
                </dict>
            </dict>
            <dict>
                <key>id</key>
                <string>3466</string>
                <key>Emitters</key>
                <dict>
                    <key>emitters</key>
                    <array>
                        <string>3468</string>
                    </array>
                </dict>
            </dict>
            <dict>
                <key>id</key>
                <string>3472</string>
                <key>Emitters</key>
                <dict>
                    <key>emitters</key>
                    <array>
                        <string>3474</string>
                    </array>
                </dict>
            </dict>
            <dict>
                <key>id</key>
                <string>3478</string>
                <key>Emitters</key>
                <dict>
                    <key>emitters</key>
                    <array>
                        <string>3480</string>
                    </array>
                </dict>
            </dict>
            <dict>
                <key>id</key>
                <string>3484</string>
                <key>Emitters</key>
                <dict>
                    <key>emitters</key>
                    <array>
                        <string>3486</string>
                    </array>
                </dict>
            </dict>
            <dict>
                <key>id</key>
                <string>3497</string>
                <key>Emitters</key>
                <dict>
                    <key>emitters</key>
                    <array>
                        <string>3499</string>
                    </array>
                </dict>
            </dict>
            <dict>
                <key>id</key>
                <string>3509</string>
                <key>Emitters</key>
                <dict>
                    <key>emitters</key>
                    <array>
                        <string>3511</string>
                    </array>
                </dict>
            </dict>
            <dict>
                <key>id</key>
                <string>3515</string>
                <key>Emitters</key>
                <dict>
                    <key>emitters</key>
                    <array>
                        <string>3517</string>
                    </array>
                </dict>
            </dict>
            <dict>
                <key>id</key>
                <string>3521</string>
                <key>Emitters</key>
                <dict>
                    <key>emitters</key>
                    <array>
                        <string>3523</string>
                    </array>
                </dict>
            </dict>
            <dict>
                <key>id</key>
                <string>3527</string>
                <key>Emitters</key>
                <dict>
                    <key>emitters</key>
                    <array>
                        <string>3529</string>
                    </array>
                </dict>
            </dict>
            <dict>
                <key>id</key>
                <string>3533</string>
                <key>Emitters</key>
                <dict>
                    <key>emitters</key>
                    <array>
                        <string>3535</string>
                    </array>
                </dict>
            </dict>
            <dict>
                <key>id</key>
                <string>3539</string>
                <key>Emitters</key>
                <dict>
                    <key>emitters</key>
                    <array>
                        <string>3541</string>
                    </array>
                </dict>
            </dict>
            <dict>
                <key>id</key>
                <string>3545</string>
                <key>Emitters</key>
                <dict>
                    <key>emitters</key>
                    <array>
                        <string>3547</string>
                    </array>
                </dict>
            </dict>
            <dict>
                <key>id</key>
                <string>3551</string>
                <key>Emitters</key>
                <dict>
                    <key>emitters</key>
                    <array>
                        <string>3553</string>
                    </array>
                </dict>
            </dict>
            <dict>
                <key>id</key>
                <string>3557</string>
                <key>Emitters</key>
                <dict>
                    <key>emitters</key>
                    <array>
                        <string>3559</string>
                    </array>
                </dict>
            </dict>
            <dict>
                <key>id</key>
                <string>3563</string>
                <key>Emitters</key>
                <dict>
                    <key>emitters</key>
                    <array>
                        <string>3565</string>
                    </array>
                </dict>
            </dict>
            <dict>
                <key>id</key>
                <string>3569</string>
                <key>Emitters</key>
                <dict>
                    <key>emitters</key>
                    <array>
                        <string>3571</string>
                    </array>
                </dict>
            </dict>
            <dict>
                <key>id</key>
                <string>3575</string>
                <key>Emitters</key>
                <dict>
                    <key>emitters</key>
                    <array>
                        <string>3577</string>
                    </array>
                </dict>
            </dict>
            <dict>
                <key>id</key>
                <string>3581</string>
                <key>Emitters</key>
                <dict>
                    <key>emitters</key>
                    <array>
                        <string>3583</string>
                    </array>
                </dict>
            </dict>
            <dict>
                <key>id</key>
                <string>3587</string>
                <key>Emitters</key>
                <dict>
                    <key>emitters</key>
                    <array>
                        <string>3589</string>
                    </array>
                </dict>
            </dict>
            <dict>
                <key>id</key>
                <string>3593</string>
                <key>Emitters</key>
                <dict>
                    <key>emitters</key>
                    <array>
                        <string>3595</string>
                    </array>
                </dict>
            </dict>
            <dict>
                <key>id</key>
                <string>3599</string>
                <key>Emitters</key>
                <dict>
                    <key>emitters</key>
                    <array>
                        <string>3601</string>
                    </array>
                </dict>
            </dict>
            <dict>
                <key>id</key>
                <string>3605</string>
                <key>Emitters</key>
                <dict>
                    <key>emitters</key>
                    <array>
                        <string>3607</string>
                    </array>
                </dict>
            </dict>
            <dict>
                <key>id</key>
                <string>3611</string>
                <key>Emitters</key>
                <dict>
                    <key>emitters</key>
                    <array>
                        <string>3613</string>
                    </array>
                </dict>
            </dict>
            <dict>
                <key>id</key>
                <string>3617</string>
                <key>Emitters</key>
                <dict>
                    <key>emitters</key>
                    <array>
                        <string>3619</string>
                    </array>
                </dict>
            </dict>
            <dict>
                <key>id</key>
                <string>3630</string>
                <key>Emitters</key>
                <dict>
                    <key>emitters</key>
                    <array>
                        <string>3632</string>
                    </array>
                </dict>
            </dict>
            <dict>
                <key>id</key>
                <string>3815</string>
                <key>Emitters</key>
                <dict>
                    <key>emitters</key>
                    <array>
                        <string>3817</string>
                    </array>
                </dict>
            </dict>
            <dict>
                <key>id</key>
                <string>3821</string>
                <key>Emitters</key>
                <dict>
                    <key>emitters</key>
                    <array>
                        <string>3823</string>
                    </array>
                </dict>
            </dict>
            <dict>
                <key>id</key>
                <string>3827</string>
                <key>Emitters</key>
                <dict>
                    <key>emitters</key>
                    <array>
                        <string>3829</string>
                    </array>
                </dict>
            </dict>
            <dict>
                <key>id</key>
                <string>3833</string>
                <key>Emitters</key>
                <dict>
                    <key>emitters</key>
                    <array>
                        <string>3835</string>
                    </array>
                </dict>
            </dict>
            <dict>
                <key>id</key>
                <string>3839</string>
                <key>Emitters</key>
                <dict>
                    <key>emitters</key>
                    <array>
                        <string>3841</string>
                    </array>
                </dict>
            </dict>
            <dict>
                <key>id</key>
                <string>3845</string>
                <key>Emitters</key>
                <dict>
                    <key>emitters</key>
                    <array>
                        <string>3847</string>
                    </array>
                </dict>
            </dict>
            <dict>
                <key>id</key>
                <string>3851</string>
                <key>Emitters</key>
                <dict>
                    <key>emitters</key>
                    <array>
                        <string>3853</string>
                    </array>
                </dict>
            </dict>
            <dict>
                <key>id</key>
                <string>3857</string>
                <key>Emitters</key>
                <dict>
                    <key>emitters</key>
                    <array>
                        <string>3859</string>
                    </array>
                </dict>
            </dict>
            <dict>
                <key>id</key>
                <string>3863</string>
                <key>Emitters</key>
                <dict>
                    <key>emitters</key>
                    <array>
                        <string>3865</string>
                    </array>
                </dict>
            </dict>
            <dict>
                <key>id</key>
                <string>3869</string>
                <key>Emitters</key>
                <dict>
                    <key>emitters</key>
                    <array>
                        <string>3871</string>
                    </array>
                </dict>
            </dict>
            <dict>
                <key>id</key>
                <string>3875</string>
                <key>Emitters</key>
                <dict>
                    <key>emitters</key>
                    <array>
                        <string>3877</string>
                    </array>
                </dict>
            </dict>
            <dict>
                <key>id</key>
                <string>3881</string>
                <key>Emitters</key>
                <dict>
                    <key>emitters</key>
                    <array>
                        <string>3883</string>
                    </array>
                </dict>
            </dict>
            <dict>
                <key>id</key>
                <string>3887</string>
                <key>Emitters</key>
                <dict>
                    <key>emitters</key>
                    <array>
                        <string>3889</string>
                    </array>
                </dict>
            </dict>
            <dict>
                <key>id</key>
                <string>3893</string>
                <key>Emitters</key>
                <dict>
                    <key>emitters</key>
                    <array>
                        <string>3895</string>
                    </array>
                </dict>
            </dict>
            <dict>
                <key>id</key>
                <string>3899</string>
                <key>Emitters</key>
                <dict>
                    <key>emitters</key>
                    <array>
                        <string>3901</string>
                    </array>
                </dict>
            </dict>
            <dict>
                <key>id</key>
                <string>3905</string>
                <key>Emitters</key>
                <dict>
                    <key>emitters</key>
                    <array>
                        <string>3907</string>
                    </array>
                </dict>
            </dict>
            <dict>
                <key>id</key>
                <string>3911</string>
                <key>Emitters</key>
                <dict>
                    <key>emitters</key>
                    <array>
                        <string>3913</string>
                    </array>
                </dict>
            </dict>
            <dict>
                <key>id</key>
                <string>3917</string>
                <key>Emitters</key>
                <dict>
                    <key>emitters</key>
                    <array>
                        <string>3919</string>
                    </array>
                </dict>
            </dict>
            <dict>
                <key>id</key>
                <string>3923</string>
                <key>Emitters</key>
                <dict>
                    <key>emitters</key>
                    <array>
                        <string>3925</string>
                    </array>
                </dict>
            </dict>
            <dict>
                <key>id</key>
                <string>3936</string>
                <key>Emitters</key>
                <dict>
                    <key>emitters</key>
                    <array>
                        <string>3938</string>
                    </array>
                </dict>
            </dict>
            <dict>
                <key>id</key>
                <string>3948</string>
                <key>Emitters</key>
                <dict>
                    <key>emitters</key>
                    <array>
                        <string>3950</string>
                    </array>
                </dict>
            </dict>
            <dict>
                <key>id</key>
                <string>3954</string>
                <key>Emitters</key>
                <dict>
                    <key>emitters</key>
                    <array>
                        <string>3956</string>
                    </array>
                </dict>
            </dict>
            <dict>
                <key>id</key>
                <string>3960</string>
                <key>Emitters</key>
                <dict>
                    <key>emitters</key>
                    <array>
                        <string>3962</string>
                    </array>
                </dict>
            </dict>
            <dict>
                <key>id</key>
                <string>3966</string>
                <key>Emitters</key>
                <dict>
                    <key>emitters</key>
                    <array>
                        <string>3968</string>
                    </array>
                </dict>
            </dict>
            <dict>
                <key>id</key>
                <string>3972</string>
                <key>Emitters</key>
                <dict>
                    <key>emitters</key>
                    <array>
                        <string>3974</string>
                    </array>
                </dict>
            </dict>
            <dict>
                <key>id</key>
                <string>3978</string>
                <key>Emitters</key>
                <dict>
                    <key>emitters</key>
                    <array>
                        <string>3980</string>
                    </array>
                </dict>
            </dict>
            <dict>
                <key>id</key>
                <string>3984</string>
                <key>Emitters</key>
                <dict>
                    <key>emitters</key>
                    <array>
                        <string>3986</string>
                    </array>
                </dict>
            </dict>
            <dict>
                <key>id</key>
                <string>3990</string>
                <key>Emitters</key>
                <dict>
                    <key>emitters</key>
                    <array>
                        <string>3992</string>
                    </array>
                </dict>
            </dict>
            <dict>
                <key>id</key>
                <string>3996</string>
                <key>Emitters</key>
                <dict>
                    <key>emitters</key>
                    <array>
                        <string>3998</string>
                    </array>
                </dict>
            </dict>
            <dict>
                <key>id</key>
                <string>4002</string>
                <key>Emitters</key>
                <dict>
                    <key>emitters</key>
                    <array>
                        <string>4004</string>
                    </array>
                </dict>
            </dict>
            <dict>
                <key>id</key>
                <string>4008</string>
                <key>Emitters</key>
                <dict>
                    <key>emitters</key>
                    <array>
                        <string>4010</string>
                    </array>
                </dict>
            </dict>
            <dict>
                <key>id</key>
                <string>4014</string>
                <key>Emitters</key>
                <dict>
                    <key>emitters</key>
                    <array>
                        <string>4016</string>
                    </array>
                </dict>
            </dict>
            <dict>
                <key>id</key>
                <string>4020</string>
                <key>Emitters</key>
                <dict>
                    <key>emitters</key>
                    <array>
                        <string>4022</string>
                    </array>
                </dict>
            </dict>
            <dict>
                <key>id</key>
                <string>4026</string>
                <key>Emitters</key>
                <dict>
                    <key>emitters</key>
                    <array>
                        <string>4028</string>
                    </array>
                </dict>
            </dict>
            <dict>
                <key>id</key>
                <string>4032</string>
                <key>Emitters</key>
                <dict>
                    <key>emitters</key>
                    <array>
                        <string>4034</string>
                    </array>
                </dict>
            </dict>
            <dict>
                <key>id</key>
                <string>4038</string>
                <key>Emitters</key>
                <dict>
                    <key>emitters</key>
                    <array>
                        <string>4040</string>
                    </array>
                </dict>
            </dict>
            <dict>
                <key>id</key>
                <string>4044</string>
                <key>Emitters</key>
                <dict>
                    <key>emitters</key>
                    <array>
                        <string>4046</string>
                    </array>
                </dict>
            </dict>
            <dict>
                <key>id</key>
                <string>4050</string>
                <key>Emitters</key>
                <dict>
                    <key>emitters</key>
                    <array>
                        <string>4052</string>
                    </array>
                </dict>
            </dict>
            <dict>
                <key>id</key>
                <string>4056</string>
                <key>Emitters</key>
                <dict>
                    <key>emitters</key>
                    <array>
                        <string>4058</string>
                    </array>
                </dict>
            </dict>
            <dict>
                <key>id</key>
                <string>4068</string>
                <key>Emitters</key>
                <dict>
                    <key>emitters</key>
                    <array>
                        <string>4070</string>
                    </array>
                </dict>
            </dict>
            <dict>
                <key>id</key>
                <string>4080</string>
                <key>Emitters</key>
                <dict>
                    <key>emitters</key>
                    <array>
                        <string>4082</string>
                    </array>
                </dict>
            </dict>
            <dict>
                <key>id</key>
                <string>4086</string>
                <key>Emitters</key>
                <dict>
                    <key>emitters</key>
                    <array>
                        <string>4088</string>
                    </array>
                </dict>
            </dict>
            <dict>
                <key>id</key>
                <string>4092</string>
                <key>Emitters</key>
                <dict>
                    <key>emitters</key>
                    <array>
                        <string>4094</string>
                    </array>
                </dict>
            </dict>
            <dict>
                <key>id</key>
                <string>4098</string>
                <key>Emitters</key>
                <dict>
                    <key>emitters</key>
                    <array>
                        <string>4100</string>
                    </array>
                </dict>
            </dict>
            <dict>
                <key>id</key>
                <string>4104</string>
                <key>Emitters</key>
                <dict>
                    <key>emitters</key>
                    <array>
                        <string>4106</string>
                    </array>
                </dict>
            </dict>
            <dict>
                <key>id</key>
                <string>4110</string>
                <key>Emitters</key>
                <dict>
                    <key>emitters</key>
                    <array>
                        <string>4112</string>
                    </array>
                </dict>
            </dict>
            <dict>
                <key>id</key>
                <string>4116</string>
                <key>Emitters</key>
                <dict>
                    <key>emitters</key>
                    <array>
                        <string>4118</string>
                    </array>
                </dict>
            </dict>
            <dict>
                <key>id</key>
                <string>4122</string>
                <key>Emitters</key>
                <dict>
                    <key>emitters</key>
                    <array>
                        <string>4124</string>
                    </array>
                </dict>
            </dict>
            <dict>
                <key>id</key>
                <string>4128</string>
                <key>Emitters</key>
                <dict>
                    <key>emitters</key>
                    <array>
                        <string>4130</string>
                    </array>
                </dict>
            </dict>
            <dict>
                <key>id</key>
                <string>4134</string>
                <key>Emitters</key>
                <dict>
                    <key>emitters</key>
                    <array>
                        <string>4136</string>
                    </array>
                </dict>
            </dict>
            <dict>
                <key>id</key>
                <string>4140</string>
                <key>Emitters</key>
                <dict>
                    <key>emitters</key>
                    <array>
                        <string>4142</string>
                    </array>
                </dict>
            </dict>
            <dict>
                <key>id</key>
                <string>4146</string>
                <key>Emitters</key>
                <dict>
                    <key>emitters</key>
                    <array>
                        <string>4148</string>
                    </array>
                </dict>
            </dict>
            <dict>
                <key>id</key>
                <string>4152</string>
                <key>Emitters</key>
                <dict>
                    <key>emitters</key>
                    <array>
                        <string>4154</string>
                    </array>
                </dict>
            </dict>
            <dict>
                <key>id</key>
                <string>4158</string>
                <key>Emitters</key>
                <dict>
                    <key>emitters</key>
                    <array>
                        <string>4160</string>
                    </array>
                </dict>
            </dict>
            <dict>
                <key>id</key>
                <string>4164</string>
                <key>Emitters</key>
                <dict>
                    <key>emitters</key>
                    <array>
                        <string>4166</string>
                    </array>
                </dict>
            </dict>
            <dict>
                <key>id</key>
                <string>4170</string>
                <key>Emitters</key>
                <dict>
                    <key>emitters</key>
                    <array>
                        <string>4172</string>
                    </array>
                </dict>
            </dict>
            <dict>
                <key>id</key>
                <string>4176</string>
                <key>Emitters</key>
                <dict>
                    <key>emitters</key>
                    <array>
                        <string>4178</string>
                    </array>
                </dict>
            </dict>
            <dict>
                <key>id</key>
                <string>4182</string>
                <key>Emitters</key>
                <dict>
                    <key>emitters</key>
                    <array>
                        <string>4184</string>
                    </array>
                </dict>
            </dict>
            <dict>
                <key>id</key>
                <string>4188</string>
                <key>Emitters</key>
                <dict>
                    <key>emitters</key>
                    <array>
                        <string>4190</string>
                    </array>
                </dict>
            </dict>
            <dict>
                <key>id</key>
                <string>4200</string>
                <key>Emitters</key>
                <dict>
                    <key>emitters</key>
                    <array>
                        <string>4202</string>
                    </array>
                </dict>
            </dict>
            <dict>
                <key>id</key>
                <string>4212</string>
                <key>Emitters</key>
                <dict>
                    <key>emitters</key>
                    <array>
                        <string>4214</string>
                    </array>
                </dict>
            </dict>
            <dict>
                <key>id</key>
                <string>4218</string>
                <key>Emitters</key>
                <dict>
                    <key>emitters</key>
                    <array>
                        <string>4220</string>
                    </array>
                </dict>
            </dict>
            <dict>
                <key>id</key>
                <string>4224</string>
                <key>Emitters</key>
                <dict>
                    <key>emitters</key>
                    <array>
                        <string>4226</string>
                    </array>
                </dict>
            </dict>
            <dict>
                <key>id</key>
                <string>4230</string>
                <key>Emitters</key>
                <dict>
                    <key>emitters</key>
                    <array>
                        <string>4232</string>
                    </array>
                </dict>
            </dict>
            <dict>
                <key>id</key>
                <string>4236</string>
                <key>Emitters</key>
                <dict>
                    <key>emitters</key>
                    <array>
                        <string>4238</string>
                    </array>
                </dict>
            </dict>
            <dict>
                <key>id</key>
                <string>4242</string>
                <key>Emitters</key>
                <dict>
                    <key>emitters</key>
                    <array>
                        <string>4244</string>
                    </array>
                </dict>
            </dict>
            <dict>
                <key>id</key>
                <string>4248</string>
                <key>Emitters</key>
                <dict>
                    <key>emitters</key>
                    <array>
                        <string>4250</string>
                    </array>
                </dict>
            </dict>
            <dict>
                <key>id</key>
                <string>4254</string>
                <key>Emitters</key>
                <dict>
                    <key>emitters</key>
                    <array>
                        <string>4256</string>
                    </array>
                </dict>
            </dict>
            <dict>
                <key>id</key>
                <string>4260</string>
                <key>Emitters</key>
                <dict>
                    <key>emitters</key>
                    <array>
                        <string>4262</string>
                    </array>
                </dict>
            </dict>
            <dict>
                <key>id</key>
                <string>4266</string>
                <key>Emitters</key>
                <dict>
                    <key>emitters</key>
                    <array>
                        <string>4268</string>
                    </array>
                </dict>
            </dict>
            <dict>
                <key>id</key>
                <string>4272</string>
                <key>Emitters</key>
                <dict>
                    <key>emitters</key>
                    <array>
                        <string>4274</string>
                    </array>
                </dict>
            </dict>
            <dict>
                <key>id</key>
                <string>4278</string>
                <key>Emitters</key>
                <dict>
                    <key>emitters</key>
                    <array>
                        <string>4280</string>
                    </array>
                </dict>
            </dict>
            <dict>
                <key>id</key>
                <string>4284</string>
                <key>Emitters</key>
                <dict>
                    <key>emitters</key>
                    <array>
                        <string>4286</string>
                    </array>
                </dict>
            </dict>
            <dict>
                <key>id</key>
                <string>4290</string>
                <key>Emitters</key>
                <dict>
                    <key>emitters</key>
                    <array>
                        <string>4292</string>
                    </array>
                </dict>
            </dict>
            <dict>
                <key>id</key>
                <string>4296</string>
                <key>Emitters</key>
                <dict>
                    <key>emitters</key>
                    <array>
                        <string>4298</string>
                    </array>
                </dict>
            </dict>
            <dict>
                <key>id</key>
                <string>4302</string>
                <key>Emitters</key>
                <dict>
                    <key>emitters</key>
                    <array>
                        <string>4304</string>
                    </array>
                </dict>
            </dict>
            <dict>
                <key>id</key>
                <string>4308</string>
                <key>Emitters</key>
                <dict>
                    <key>emitters</key>
                    <array>
                        <string>4310</string>
                    </array>
                </dict>
            </dict>
            <dict>
                <key>id</key>
                <string>4314</string>
                <key>Emitters</key>
                <dict>
                    <key>emitters</key>
                    <array>
                        <string>4316</string>
                    </array>
                </dict>
            </dict>
            <dict>
                <key>id</key>
                <string>4320</string>
                <key>Emitters</key>
                <dict>
                    <key>emitters</key>
                    <array>
                        <string>4322</string>
                    </array>
                </dict>
            </dict>
            <dict>
                <key>id</key>
                <string>4332</string>
                <key>Emitters</key>
                <dict>
                    <key>emitters</key>
                    <array>
                        <string>4334</string>
                    </array>
                </dict>
            </dict>
            <dict>
                <key>id</key>
                <string>4344</string>
                <key>Emitters</key>
                <dict>
                    <key>emitters</key>
                    <array>
                        <string>4346</string>
                    </array>
                </dict>
            </dict>
            <dict>
                <key>id</key>
                <string>4350</string>
                <key>Emitters</key>
                <dict>
                    <key>emitters</key>
                    <array>
                        <string>4352</string>
                    </array>
                </dict>
            </dict>
            <dict>
                <key>id</key>
                <string>4356</string>
                <key>Emitters</key>
                <dict>
                    <key>emitters</key>
                    <array>
                        <string>4358</string>
                    </array>
                </dict>
            </dict>
            <dict>
                <key>id</key>
                <string>4362</string>
                <key>Emitters</key>
                <dict>
                    <key>emitters</key>
                    <array>
                        <string>4364</string>
                    </array>
                </dict>
            </dict>
            <dict>
                <key>id</key>
                <string>4368</string>
                <key>Emitters</key>
                <dict>
                    <key>emitters</key>
                    <array>
                        <string>4370</string>
                    </array>
                </dict>
            </dict>
            <dict>
                <key>id</key>
                <string>4374</string>
                <key>Emitters</key>
                <dict>
                    <key>emitters</key>
                    <array>
                        <string>4376</string>
                    </array>
                </dict>
            </dict>
            <dict>
                <key>id</key>
                <string>4380</string>
                <key>Emitters</key>
                <dict>
                    <key>emitters</key>
                    <array>
                        <string>4382</string>
                    </array>
                </dict>
            </dict>
            <dict>
                <key>id</key>
                <string>4386</string>
                <key>Emitters</key>
                <dict>
                    <key>emitters</key>
                    <array>
                        <string>4388</string>
                    </array>
                </dict>
            </dict>
            <dict>
                <key>id</key>
                <string>4392</string>
                <key>Emitters</key>
                <dict>
                    <key>emitters</key>
                    <array>
                        <string>4394</string>
                    </array>
                </dict>
            </dict>
            <dict>
                <key>id</key>
                <string>4398</string>
                <key>Emitters</key>
                <dict>
                    <key>emitters</key>
                    <array>
                        <string>4400</string>
                    </array>
                </dict>
            </dict>
            <dict>
                <key>id</key>
                <string>4404</string>
                <key>Emitters</key>
                <dict>
                    <key>emitters</key>
                    <array>
                        <string>4406</string>
                    </array>
                </dict>
            </dict>
            <dict>
                <key>id</key>
                <string>4410</string>
                <key>Emitters</key>
                <dict>
                    <key>emitters</key>
                    <array>
                        <string>4412</string>
                    </array>
                </dict>
            </dict>
            <dict>
                <key>id</key>
                <string>4416</string>
                <key>Emitters</key>
                <dict>
                    <key>emitters</key>
                    <array>
                        <string>4418</string>
                    </array>
                </dict>
            </dict>
            <dict>
                <key>id</key>
                <string>4422</string>
                <key>Emitters</key>
                <dict>
                    <key>emitters</key>
                    <array>
                        <string>4424</string>
                    </array>
                </dict>
            </dict>
            <dict>
                <key>id</key>
                <string>4428</string>
                <key>Emitters</key>
                <dict>
                    <key>emitters</key>
                    <array>
                        <string>4430</string>
                    </array>
                </dict>
            </dict>
            <dict>
                <key>id</key>
                <string>4434</string>
                <key>Emitters</key>
                <dict>
                    <key>emitters</key>
                    <array>
                        <string>4436</string>
                    </array>
                </dict>
            </dict>
            <dict>
                <key>id</key>
                <string>4440</string>
                <key>Emitters</key>
                <dict>
                    <key>emitters</key>
                    <array>
                        <string>4442</string>
                    </array>
                </dict>
            </dict>
            <dict>
                <key>id</key>
                <string>4446</string>
                <key>Emitters</key>
                <dict>
                    <key>emitters</key>
                    <array>
                        <string>4448</string>
                    </array>
                </dict>
            </dict>
            <dict>
                <key>id</key>
                <string>4452</string>
                <key>Emitters</key>
                <dict>
                    <key>emitters</key>
                    <array>
                        <string>4454</string>
                    </array>
                </dict>
            </dict>
            <dict>
                <key>id</key>
                <string>4464</string>
                <key>Emitters</key>
                <dict>
                    <key>emitters</key>
                    <array>
                        <string>4466</string>
                    </array>
                </dict>
            </dict>
            <dict>
                <key>id</key>
                <string>4477</string>
                <key>Emitters</key>
                <dict>
                    <key>emitters</key>
                    <array>
                        <string>4479</string>
                    </array>
                </dict>
            </dict>
            <dict>
                <key>id</key>
                <string>4483</string>
                <key>Emitters</key>
                <dict>
                    <key>emitters</key>
                    <array>
                        <string>4485</string>
                    </array>
                </dict>
            </dict>
            <dict>
                <key>id</key>
                <string>4489</string>
                <key>Emitters</key>
                <dict>
                    <key>emitters</key>
                    <array>
                        <string>4491</string>
                    </array>
                </dict>
            </dict>
            <dict>
                <key>id</key>
                <string>4495</string>
                <key>Emitters</key>
                <dict>
                    <key>emitters</key>
                    <array>
                        <string>4497</string>
                    </array>
                </dict>
            </dict>
            <dict>
                <key>id</key>
                <string>4501</string>
                <key>Emitters</key>
                <dict>
                    <key>emitters</key>
                    <array>
                        <string>4503</string>
                    </array>
                </dict>
            </dict>
            <dict>
                <key>id</key>
                <string>4507</string>
                <key>Emitters</key>
                <dict>
                    <key>emitters</key>
                    <array>
                        <string>4509</string>
                    </array>
                </dict>
            </dict>
            <dict>
                <key>id</key>
                <string>4513</string>
                <key>Emitters</key>
                <dict>
                    <key>emitters</key>
                    <array>
                        <string>4515</string>
                    </array>
                </dict>
            </dict>
            <dict>
                <key>id</key>
                <string>4519</string>
                <key>Emitters</key>
                <dict>
                    <key>emitters</key>
                    <array>
                        <string>4521</string>
                    </array>
                </dict>
            </dict>
            <dict>
                <key>id</key>
                <string>4525</string>
                <key>Emitters</key>
                <dict>
                    <key>emitters</key>
                    <array>
                        <string>4527</string>
                    </array>
                </dict>
            </dict>
            <dict>
                <key>id</key>
                <string>4531</string>
                <key>Emitters</key>
                <dict>
                    <key>emitters</key>
                    <array>
                        <string>4533</string>
                    </array>
                </dict>
            </dict>
            <dict>
                <key>id</key>
                <string>4537</string>
                <key>Emitters</key>
                <dict>
                    <key>emitters</key>
                    <array>
                        <string>4539</string>
                    </array>
                </dict>
            </dict>
            <dict>
                <key>id</key>
                <string>4543</string>
                <key>Emitters</key>
                <dict>
                    <key>emitters</key>
                    <array>
                        <string>4545</string>
                    </array>
                </dict>
            </dict>
            <dict>
                <key>id</key>
                <string>4549</string>
                <key>Emitters</key>
                <dict>
                    <key>emitters</key>
                    <array>
                        <string>4551</string>
                    </array>
                </dict>
            </dict>
            <dict>
                <key>id</key>
                <string>4555</string>
                <key>Emitters</key>
                <dict>
                    <key>emitters</key>
                    <array>
                        <string>4557</string>
                    </array>
                </dict>
            </dict>
            <dict>
                <key>id</key>
                <string>4561</string>
                <key>Emitters</key>
                <dict>
                    <key>emitters</key>
                    <array>
                        <string>4563</string>
                    </array>
                </dict>
            </dict>
            <dict>
                <key>id</key>
                <string>4567</string>
                <key>Emitters</key>
                <dict>
                    <key>emitters</key>
                    <array>
                        <string>4569</string>
                    </array>
                </dict>
            </dict>
            <dict>
                <key>id</key>
                <string>4573</string>
                <key>Emitters</key>
                <dict>
                    <key>emitters</key>
                    <array>
                        <string>4575</string>
                    </array>
                </dict>
            </dict>
            <dict>
                <key>id</key>
                <string>4579</string>
                <key>Emitters</key>
                <dict>
                    <key>emitters</key>
                    <array>
                        <string>4581</string>
                    </array>
                </dict>
            </dict>
            <dict>
                <key>id</key>
                <string>4585</string>
                <key>Emitters</key>
                <dict>
                    <key>emitters</key>
                    <array>
                        <string>4587</string>
                    </array>
                </dict>
            </dict>
            <dict>
                <key>id</key>
                <string>4597</string>
                <key>Emitters</key>
                <dict>
                    <key>emitters</key>
                    <array>
                        <string>4599</string>
                    </array>
                </dict>
            </dict>
            <dict>
                <key>id</key>
                <string>4609</string>
                <key>Emitters</key>
                <dict>
                    <key>emitters</key>
                    <array>
                        <string>4611</string>
                    </array>
                </dict>
            </dict>
            <dict>
                <key>id</key>
                <string>4615</string>
                <key>Emitters</key>
                <dict>
                    <key>emitters</key>
                    <array>
                        <string>4617</string>
                    </array>
                </dict>
            </dict>
            <dict>
                <key>id</key>
                <string>4621</string>
                <key>Emitters</key>
                <dict>
                    <key>emitters</key>
                    <array>
                        <string>4623</string>
                    </array>
                </dict>
            </dict>
            <dict>
                <key>id</key>
                <string>4627</string>
                <key>Emitters</key>
                <dict>
                    <key>emitters</key>
                    <array>
                        <string>4629</string>
                    </array>
                </dict>
            </dict>
            <dict>
                <key>id</key>
                <string>4633</string>
                <key>Emitters</key>
                <dict>
                    <key>emitters</key>
                    <array>
                        <string>4635</string>
                    </array>
                </dict>
            </dict>
            <dict>
                <key>id</key>
                <string>4639</string>
                <key>Emitters</key>
                <dict>
                    <key>emitters</key>
                    <array>
                        <string>4641</string>
                    </array>
                </dict>
            </dict>
            <dict>
                <key>id</key>
                <string>4645</string>
                <key>Emitters</key>
                <dict>
                    <key>emitters</key>
                    <array>
                        <string>4647</string>
                    </array>
                </dict>
            </dict>
            <dict>
                <key>id</key>
                <string>4651</string>
                <key>Emitters</key>
                <dict>
                    <key>emitters</key>
                    <array>
                        <string>4653</string>
                    </array>
                </dict>
            </dict>
            <dict>
                <key>id</key>
                <string>4657</string>
                <key>Emitters</key>
                <dict>
                    <key>emitters</key>
                    <array>
                        <string>4659</string>
                    </array>
                </dict>
            </dict>
            <dict>
                <key>id</key>
                <string>4663</string>
                <key>Emitters</key>
                <dict>
                    <key>emitters</key>
                    <array>
                        <string>4665</string>
                    </array>
                </dict>
            </dict>
            <dict>
                <key>id</key>
                <string>4669</string>
                <key>Emitters</key>
                <dict>
                    <key>emitters</key>
                    <array>
                        <string>4671</string>
                    </array>
                </dict>
            </dict>
            <dict>
                <key>id</key>
                <string>4675</string>
                <key>Emitters</key>
                <dict>
                    <key>emitters</key>
                    <array>
                        <string>4677</string>
                    </array>
                </dict>
            </dict>
            <dict>
                <key>id</key>
                <string>4681</string>
                <key>Emitters</key>
                <dict>
                    <key>emitters</key>
                    <array>
                        <string>4683</string>
                    </array>
                </dict>
            </dict>
            <dict>
                <key>id</key>
                <string>4687</string>
                <key>Emitters</key>
                <dict>
                    <key>emitters</key>
                    <array>
                        <string>4689</string>
                    </array>
                </dict>
            </dict>
            <dict>
                <key>id</key>
                <string>4693</string>
                <key>Emitters</key>
                <dict>
                    <key>emitters</key>
                    <array>
                        <string>4695</string>
                    </array>
                </dict>
            </dict>
            <dict>
                <key>id</key>
                <string>4699</string>
                <key>Emitters</key>
                <dict>
                    <key>emitters</key>
                    <array>
                        <string>4701</string>
                    </array>
                </dict>
            </dict>
            <dict>
                <key>id</key>
                <string>4705</string>
                <key>Emitters</key>
                <dict>
                    <key>emitters</key>
                    <array>
                        <string>4707</string>
                    </array>
                </dict>
            </dict>
            <dict>
                <key>id</key>
                <string>4711</string>
                <key>Emitters</key>
                <dict>
                    <key>emitters</key>
                    <array>
                        <string>4713</string>
                    </array>
                </dict>
            </dict>
            <dict>
                <key>id</key>
                <string>4717</string>
                <key>Emitters</key>
                <dict>
                    <key>emitters</key>
                    <array>
                        <string>4719</string>
                    </array>
                </dict>
            </dict>
            <dict>
                <key>id</key>
                <string>5794</string>
                <key>Emitters</key>
                <dict>
                    <key>emitters</key>
                    <array>
                        <string>5796</string>
                    </array>
                </dict>
            </dict>
        </array>
    </dict>
</plist>
